LICENSE
MANIFEST.in
README.rst
requirements-py33.txt
requirements-test.txt
requirements.txt
setup.py
gisht/__init__.py
gisht/__main__.py
gisht/ext.py
gisht/github.py
gisht/util.py
gisht.egg-info/PKG-INFO
gisht.egg-info/SOURCES.txt
gisht.egg-info/dependency_links.txt
gisht.egg-info/entry_points.txt
gisht.egg-info/not-zip-safe
gisht.egg-info/requires.txt
gisht.egg-info/top_level.txt
gisht/args/__init__.py
gisht/args/autocomplete.py
gisht/args/data.py
gisht/args/parser.py
gisht/gists/__init__.py
gisht/gists/cache.py
gisht/gists/info.py
gisht/gists/misc.py
gisht/gists/run.py
tests/test_gists/__init__.py
tests/test_gists/test_cache.py
tests/test_gists/test_run.py